orpheus/__init__.py
Orpheus-0.0.1.dist-info/LICENSE
Orpheus-0.0.1.dist-info/METADATA
Orpheus-0.0.1.dist-info/WHEEL
Orpheus-0.0.1.dist-info/top_level.txt
Orpheus-0.0.1.dist-info/RECORD
