Metadata-Version: 2.1
Name: Orpheus
Version: 0.0.1
Summary: An intelligent music retrieval engine
Home-page: https://github.com/pypa/sampleproject
Author: Harish Kumar
Author-email: harishk1908@gmail.com
License: UNKNOWN
Platform: UNKNOWN
Classifier: Programming Language :: Python :: 3
Classifier: License :: OSI Approved :: MIT License
Classifier: Operating System :: OS Independent
